sparrow_zoo/__init__.py
sparrow_zoo/base.py
sparrow_zoo/base_test.py
sparrow_zoo/holdouts.py
sparrow_zoo/transforms.py
sparrow_zoo/utils.py
sparrow_zoo/utils_test.py
sparrow_zoo/detector/__init__.py
sparrow_zoo/detector/base.py
sparrow_zoo/detector/dataset.py
sparrow_zoo/detector/fcos.py
sparrow_zoo/detector/fcos_test.py
sparrow_zoo/detector/retinanet.py
sparrow_zoo/detector/retinanet_test.py
sparrow_zoo-0.1.4.dist-info/LICENSE
sparrow_zoo-0.1.4.dist-info/METADATA
sparrow_zoo-0.1.4.dist-info/WHEEL
sparrow_zoo-0.1.4.dist-info/top_level.txt
sparrow_zoo-0.1.4.dist-info/RECORD
