Metadata-Version: 2.1
Name: sparrow-zoo
Version: 0.1.4
Author: Sparrow Computing
Author-email: ben@sparrow.dev
License-File: LICENSE
Requires-Dist: numpy
Requires-Dist: pyfarmhash
Requires-Dist: scipy
Requires-Dist: sparrow-datums
Requires-Dist: timm
Requires-Dist: torch (<1.13.0)
Requires-Dist: torchvision
Provides-Extra: dev
Requires-Dist: black ; extra == 'dev'
Requires-Dist: isort ; extra == 'dev'
Requires-Dist: jupyter ; extra == 'dev'
Requires-Dist: matplotlib ; extra == 'dev'
Requires-Dist: onnxruntime ; extra == 'dev'
Requires-Dist: pydocstyle ; extra == 'dev'
Requires-Dist: pylint ; extra == 'dev'
Requires-Dist: pytest ; extra == 'dev'
Requires-Dist: pytest-cov ; extra == 'dev'
Provides-Extra: gpu
Requires-Dist: nvidia-tensorrt ; extra == 'gpu'
Requires-Dist: onnx ; extra == 'gpu'
Requires-Dist: onnx-graphsurgeon ; extra == 'gpu'
Requires-Dist: polygraphy ; extra == 'gpu'
